[
  {
    "episode": 0,
    "rewards": {
      "adversary_0": 0.0,
      "adversary_1": 0.0,
      "adversary_2": 0.0,
      "agent_0": -15.881359513064158
    },
    "captures": 0,
    "done_reason": "max_cycles"
  },
  {
    "episode": 1,
    "rewards": {
      "adversary_0": 30.0,
      "adversary_1": 30.0,
      "adversary_2": 30.0,
      "agent_0": -180.20822518479616
    },
    "captures": 3,
    "done_reason": "capture"
  },
  {
    "episode": 2,
    "rewards": {
      "adversary_0": 0.0,
      "adversary_1": 0.0,
      "adversary_2": 0.0,
      "agent_0": -58.01993988238499
    },
    "captures": 0,
    "done_reason": "max_cycles"
  },
  {
    "episode": 3,
    "rewards": {
      "adversary_0": 10.0,
      "adversary_1": 10.0,
      "adversary_2": 10.0,
      "agent_0": -10.0
    },
    "captures": 1,
    "done_reason": "capture"
  },
  {
    "episode": 4,
    "rewards": {
      "adversary_0": 30.0,
      "adversary_1": 30.0,
      "adversary_2": 30.0,
      "agent_0": -49.46013129052621
    },
    "captures": 3,
    "done_reason": "capture"
  },
  {
    "episode": 5,
    "rewards": {
      "adversary_0": 50.0,
      "adversary_1": 50.0,
      "adversary_2": 50.0,
      "agent_0": -286.7001394632343
    },
    "captures": 5,
    "done_reason": "capture"
  },
  {
    "episode": 6,
    "rewards": {
      "adversary_0": 0.0,
      "adversary_1": 0.0,
      "adversary_2": 0.0,
      "agent_0": 0.0
    },
    "captures": 0,
    "done_reason": "max_cycles"
  },
  {
    "episode": 7,
    "rewards": {
      "adversary_0": 0.0,
      "adversary_1": 0.0,
      "adversary_2": 0.0,
      "agent_0": -12.816086891443629
    },
    "captures": 0,
    "done_reason": "max_cycles"
  },
  {
    "episode": 8,
    "rewards": {
      "adversary_0": 30.0,
      "adversary_1": 30.0,
      "adversary_2": 30.0,
      "agent_0": -126.74751233779563
    },
    "captures": 3,
    "done_reason": "capture"
  },
  {
    "episode": 9,
    "rewards": {
      "adversary_0": 0.0,
      "adversary_1": 0.0,
      "adversary_2": 0.0,
      "agent_0": -300.3556857780178
    },
    "captures": 0,
    "done_reason": "max_cycles"
  },
  {
    "episode": 10,
    "rewards": {
      "adversary_0": 0.0,
      "adversary_1": 0.0,
      "adversary_2": 0.0,
      "agent_0": -167.58472099146837
    },
    "captures": 0,
    "done_reason": "max_cycles"
  },
  {
    "episode": 11,
    "rewards": {
      "adversary_0": 30.0,
      "adversary_1": 30.0,
      "adversary_2": 30.0,
      "agent_0": -30.0
    },
    "captures": 3,
    "done_reason": "capture"
  },
  {
    "episode": 12,
    "rewards": {
      "adversary_0": 0.0,
      "adversary_1": 0.0,
      "adversary_2": 0.0,
      "agent_0": -522.7169662053254
    },
    "captures": 0,
    "done_reason": "max_cycles"
  },
  {
    "episode": 13,
    "rewards": {
      "adversary_0": 20.0,
      "adversary_1": 20.0,
      "adversary_2": 20.0,
      "agent_0": -58.88332950979758
    },
    "captures": 2,
    "done_reason": "capture"
  },
  {
    "episode": 14,
    "rewards": {
      "adversary_0": 30.0,
      "adversary_1": 30.0,
      "adversary_2": 30.0,
      "agent_0": -30.0
    },
    "captures": 3,
    "done_reason": "capture"
  },
  {
    "episode": 15,
    "rewards": {
      "adversary_0": 0.0,
      "adversary_1": 0.0,
      "adversary_2": 0.0,
      "agent_0": -47.37282352776055
    },
    "captures": 0,
    "done_reason": "max_cycles"
  },
  {
    "episode": 16,
    "rewards": {
      "adversary_0": 0.0,
      "adversary_1": 0.0,
      "adversary_2": 0.0,
      "agent_0": -28.559548510179223
    },
    "captures": 0,
    "done_reason": "max_cycles"
  },
  {
    "episode": 17,
    "rewards": {
      "adversary_0": 0.0,
      "adversary_1": 0.0,
      "adversary_2": 0.0,
      "agent_0": -210.63650187922786
    },
    "captures": 0,
    "done_reason": "max_cycles"
  },
  {
    "episode": 18,
    "rewards": {
      "adversary_0": 0.0,
      "adversary_1": 0.0,
      "adversary_2": 0.0,
      "agent_0": -180.4585222195889
    },
    "captures": 0,
    "done_reason": "max_cycles"
  },
  {
    "episode": 19,
    "rewards": {
      "adversary_0": 30.0,
      "adversary_1": 30.0,
      "adversary_2": 30.0,
      "agent_0": -30.0
    },
    "captures": 3,
    "done_reason": "capture"
  },
  {
    "episode": 20,
    "rewards": {
      "adversary_0": 0.0,
      "adversary_1": 0.0,
      "adversary_2": 0.0,
      "agent_0": 0.0
    },
    "captures": 0,
    "done_reason": "max_cycles"
  },
  {
    "episode": 21,
    "rewards": {
      "adversary_0": 0.0,
      "adversary_1": 0.0,
      "adversary_2": 0.0,
      "agent_0": -737.98511963532
    },
    "captures": 0,
    "done_reason": "max_cycles"
  },
  {
    "episode": 22,
    "rewards": {
      "adversary_0": 0.0,
      "adversary_1": 0.0,
      "adversary_2": 0.0,
      "agent_0": -53.23929673630926
    },
    "captures": 0,
    "done_reason": "max_cycles"
  },
  {
    "episode": 23,
    "rewards": {
      "adversary_0": 0.0,
      "adversary_1": 0.0,
      "adversary_2": 0.0,
      "agent_0": -1.040134069298091
    },
    "captures": 0,
    "done_reason": "max_cycles"
  },
  {
    "episode": 24,
    "rewards": {
      "adversary_0": 0.0,
      "adversary_1": 0.0,
      "adversary_2": 0.0,
      "agent_0": -69.86580085565207
    },
    "captures": 0,
    "done_reason": "max_cycles"
  },
  {
    "episode": 25,
    "rewards": {
      "adversary_0": 30.0,
      "adversary_1": 30.0,
      "adversary_2": 30.0,
      "agent_0": -30.91642711655423
    },
    "captures": 3,
    "done_reason": "capture"
  },
  {
    "episode": 26,
    "rewards": {
      "adversary_0": 0.0,
      "adversary_1": 0.0,
      "adversary_2": 0.0,
      "agent_0": 0.0
    },
    "captures": 0,
    "done_reason": "max_cycles"
  },
  {
    "episode": 27,
    "rewards": {
      "adversary_0": 0.0,
      "adversary_1": 0.0,
      "adversary_2": 0.0,
      "agent_0": -290.9769988091071
    },
    "captures": 0,
    "done_reason": "max_cycles"
  },
  {
    "episode": 28,
    "rewards": {
      "adversary_0": 0.0,
      "adversary_1": 0.0,
      "adversary_2": 0.0,
      "agent_0": -1.0331188784944711
    },
    "captures": 0,
    "done_reason": "max_cycles"
  },
  {
    "episode": 29,
    "rewards": {
      "adversary_0": 0.0,
      "adversary_1": 0.0,
      "adversary_2": 0.0,
      "agent_0": -7.344672096842461
    },
    "captures": 0,
    "done_reason": "max_cycles"
  },
  {
    "episode": 30,
    "rewards": {
      "adversary_0": 0.0,
      "adversary_1": 0.0,
      "adversary_2": 0.0,
      "agent_0": -34.76301940959089
    },
    "captures": 0,
    "done_reason": "max_cycles"
  },
  {
    "episode": 31,
    "rewards": {
      "adversary_0": 0.0,
      "adversary_1": 0.0,
      "adversary_2": 0.0,
      "agent_0": -13.141012498020954
    },
    "captures": 0,
    "done_reason": "max_cycles"
  },
  {
    "episode": 32,
    "rewards": {
      "adversary_0": 0.0,
      "adversary_1": 0.0,
      "adversary_2": 0.0,
      "agent_0": -218.37886817742026
    },
    "captures": 0,
    "done_reason": "max_cycles"
  },
  {
    "episode": 33,
    "rewards": {
      "adversary_0": 0.0,
      "adversary_1": 0.0,
      "adversary_2": 0.0,
      "agent_0": 0.0
    },
    "captures": 0,
    "done_reason": "max_cycles"
  },
  {
    "episode": 34,
    "rewards": {
      "adversary_0": 0.0,
      "adversary_1": 0.0,
      "adversary_2": 0.0,
      "agent_0": -13.183643402224993
    },
    "captures": 0,
    "done_reason": "max_cycles"
  },
  {
    "episode": 35,
    "rewards": {
      "adversary_0": 30.0,
      "adversary_1": 30.0,
      "adversary_2": 30.0,
      "agent_0": -137.06422656250618
    },
    "captures": 3,
    "done_reason": "capture"
  },
  {
    "episode": 36,
    "rewards": {
      "adversary_0": 0.0,
      "adversary_1": 0.0,
      "adversary_2": 0.0,
      "agent_0": -33.69164562920981
    },
    "captures": 0,
    "done_reason": "max_cycles"
  },
  {
    "episode": 37,
    "rewards": {
      "adversary_0": 30.0,
      "adversary_1": 30.0,
      "adversary_2": 30.0,
      "agent_0": -308.4938674627658
    },
    "captures": 3,
    "done_reason": "capture"
  },
  {
    "episode": 38,
    "rewards": {
      "adversary_0": 30.0,
      "adversary_1": 30.0,
      "adversary_2": 30.0,
      "agent_0": -30.0
    },
    "captures": 3,
    "done_reason": "capture"
  },
  {
    "episode": 39,
    "rewards": {
      "adversary_0": 0.0,
      "adversary_1": 0.0,
      "adversary_2": 0.0,
      "agent_0": -69.52677881252002
    },
    "captures": 0,
    "done_reason": "max_cycles"
  },
  {
    "episode": 40,
    "rewards": {
      "adversary_0": 0.0,
      "adversary_1": 0.0,
      "adversary_2": 0.0,
      "agent_0": -379.4886569215819
    },
    "captures": 0,
    "done_reason": "max_cycles"
  },
  {
    "episode": 41,
    "rewards": {
      "adversary_0": 0.0,
      "adversary_1": 0.0,
      "adversary_2": 0.0,
      "agent_0": -56.30745920928811
    },
    "captures": 0,
    "done_reason": "max_cycles"
  },
  {
    "episode": 42,
    "rewards": {
      "adversary_0": 30.0,
      "adversary_1": 30.0,
      "adversary_2": 30.0,
      "agent_0": -49.74155643946532
    },
    "captures": 3,
    "done_reason": "capture"
  },
  {
    "episode": 43,
    "rewards": {
      "adversary_0": 30.0,
      "adversary_1": 30.0,
      "adversary_2": 30.0,
      "agent_0": -43.65069099298937
    },
    "captures": 3,
    "done_reason": "capture"
  },
  {
    "episode": 44,
    "rewards": {
      "adversary_0": 0.0,
      "adversary_1": 0.0,
      "adversary_2": 0.0,
      "agent_0": 0.0
    },
    "captures": 0,
    "done_reason": "max_cycles"
  },
  {
    "episode": 45,
    "rewards": {
      "adversary_0": 0.0,
      "adversary_1": 0.0,
      "adversary_2": 0.0,
      "agent_0": -721.4910329890356
    },
    "captures": 0,
    "done_reason": "max_cycles"
  },
  {
    "episode": 46,
    "rewards": {
      "adversary_0": 0.0,
      "adversary_1": 0.0,
      "adversary_2": 0.0,
      "agent_0": -29.233577963188434
    },
    "captures": 0,
    "done_reason": "max_cycles"
  },
  {
    "episode": 47,
    "rewards": {
      "adversary_0": 50.0,
      "adversary_1": 50.0,
      "adversary_2": 50.0,
      "agent_0": -50.0
    },
    "captures": 5,
    "done_reason": "capture"
  },
  {
    "episode": 48,
    "rewards": {
      "adversary_0": 0.0,
      "adversary_1": 0.0,
      "adversary_2": 0.0,
      "agent_0": -3.902339282282256
    },
    "captures": 0,
    "done_reason": "max_cycles"
  },
  {
    "episode": 49,
    "rewards": {
      "adversary_0": 0.0,
      "adversary_1": 0.0,
      "adversary_2": 0.0,
      "agent_0": -219.7463072221177
    },
    "captures": 0,
    "done_reason": "max_cycles"
  },
  {
    "episode": 50,
    "rewards": {
      "adversary_0": 30.0,
      "adversary_1": 30.0,
      "adversary_2": 30.0,
      "agent_0": -30.0
    },
    "captures": 3,
    "done_reason": "capture"
  },
  {
    "episode": 51,
    "rewards": {
      "adversary_0": 0.0,
      "adversary_1": 0.0,
      "adversary_2": 0.0,
      "agent_0": -215.823816184031
    },
    "captures": 0,
    "done_reason": "max_cycles"
  },
  {
    "episode": 52,
    "rewards": {
      "adversary_0": 0.0,
      "adversary_1": 0.0,
      "adversary_2": 0.0,
      "agent_0": 0.0
    },
    "captures": 0,
    "done_reason": "max_cycles"
  },
  {
    "episode": 53,
    "rewards": {
      "adversary_0": 0.0,
      "adversary_1": 0.0,
      "adversary_2": 0.0,
      "agent_0": -23.806021128948256
    },
    "captures": 0,
    "done_reason": "max_cycles"
  },
  {
    "episode": 54,
    "rewards": {
      "adversary_0": 0.0,
      "adversary_1": 0.0,
      "adversary_2": 0.0,
      "agent_0": -44.718941606238886
    },
    "captures": 0,
    "done_reason": "max_cycles"
  },
  {
    "episode": 55,
    "rewards": {
      "adversary_0": 70.0,
      "adversary_1": 70.0,
      "adversary_2": 70.0,
      "agent_0": -104.14456367794719
    },
    "captures": 7,
    "done_reason": "capture"
  },
  {
    "episode": 56,
    "rewards": {
      "adversary_0": 0.0,
      "adversary_1": 0.0,
      "adversary_2": 0.0,
      "agent_0": -0.8803316615636159
    },
    "captures": 0,
    "done_reason": "max_cycles"
  },
  {
    "episode": 57,
    "rewards": {
      "adversary_0": 0.0,
      "adversary_1": 0.0,
      "adversary_2": 0.0,
      "agent_0": -1.2277611471922478
    },
    "captures": 0,
    "done_reason": "max_cycles"
  },
  {
    "episode": 58,
    "rewards": {
      "adversary_0": 0.0,
      "adversary_1": 0.0,
      "adversary_2": 0.0,
      "agent_0": -322.65577493989025
    },
    "captures": 0,
    "done_reason": "max_cycles"
  },
  {
    "episode": 59,
    "rewards": {
      "adversary_0": 0.0,
      "adversary_1": 0.0,
      "adversary_2": 0.0,
      "agent_0": -15.29988790335229
    },
    "captures": 0,
    "done_reason": "max_cycles"
  },
  {
    "episode": 60,
    "rewards": {
      "adversary_0": 0.0,
      "adversary_1": 0.0,
      "adversary_2": 0.0,
      "agent_0": -89.94294698362194
    },
    "captures": 0,
    "done_reason": "max_cycles"
  },
  {
    "episode": 61,
    "rewards": {
      "adversary_0": 50.0,
      "adversary_1": 50.0,
      "adversary_2": 50.0,
      "agent_0": -50.129424696320925
    },
    "captures": 5,
    "done_reason": "capture"
  },
  {
    "episode": 62,
    "rewards": {
      "adversary_0": 0.0,
      "adversary_1": 0.0,
      "adversary_2": 0.0,
      "agent_0": -356.86013934902985
    },
    "captures": 0,
    "done_reason": "max_cycles"
  },
  {
    "episode": 63,
    "rewards": {
      "adversary_0": 30.0,
      "adversary_1": 30.0,
      "adversary_2": 30.0,
      "agent_0": -164.5935366109107
    },
    "captures": 3,
    "done_reason": "capture"
  },
  {
    "episode": 64,
    "rewards": {
      "adversary_0": 0.0,
      "adversary_1": 0.0,
      "adversary_2": 0.0,
      "agent_0": -73.5737539322626
    },
    "captures": 0,
    "done_reason": "max_cycles"
  },
  {
    "episode": 65,
    "rewards": {
      "adversary_0": 0.0,
      "adversary_1": 0.0,
      "adversary_2": 0.0,
      "agent_0": -98.88445335495562
    },
    "captures": 0,
    "done_reason": "max_cycles"
  },
  {
    "episode": 66,
    "rewards": {
      "adversary_0": 0.0,
      "adversary_1": 0.0,
      "adversary_2": 0.0,
      "agent_0": -0.32712966497725926
    },
    "captures": 0,
    "done_reason": "max_cycles"
  },
  {
    "episode": 67,
    "rewards": {
      "adversary_0": 0.0,
      "adversary_1": 0.0,
      "adversary_2": 0.0,
      "agent_0": -140.95038754311815
    },
    "captures": 0,
    "done_reason": "max_cycles"
  },
  {
    "episode": 68,
    "rewards": {
      "adversary_0": 0.0,
      "adversary_1": 0.0,
      "adversary_2": 0.0,
      "agent_0": 0.0
    },
    "captures": 0,
    "done_reason": "max_cycles"
  },
  {
    "episode": 69,
    "rewards": {
      "adversary_0": 0.0,
      "adversary_1": 0.0,
      "adversary_2": 0.0,
      "agent_0": -238.6575178498113
    },
    "captures": 0,
    "done_reason": "max_cycles"
  },
  {
    "episode": 70,
    "rewards": {
      "adversary_0": 20.0,
      "adversary_1": 20.0,
      "adversary_2": 20.0,
      "agent_0": -39.895255357063334
    },
    "captures": 2,
    "done_reason": "capture"
  },
  {
    "episode": 71,
    "rewards": {
      "adversary_0": 30.0,
      "adversary_1": 30.0,
      "adversary_2": 30.0,
      "agent_0": -90.49244615821696
    },
    "captures": 3,
    "done_reason": "capture"
  },
  {
    "episode": 72,
    "rewards": {
      "adversary_0": 10.0,
      "adversary_1": 10.0,
      "adversary_2": 10.0,
      "agent_0": -10.0
    },
    "captures": 1,
    "done_reason": "capture"
  },
  {
    "episode": 73,
    "rewards": {
      "adversary_0": 0.0,
      "adversary_1": 0.0,
      "adversary_2": 0.0,
      "agent_0": 0.0
    },
    "captures": 0,
    "done_reason": "max_cycles"
  },
  {
    "episode": 74,
    "rewards": {
      "adversary_0": 0.0,
      "adversary_1": 0.0,
      "adversary_2": 0.0,
      "agent_0": -62.30003024229569
    },
    "captures": 0,
    "done_reason": "max_cycles"
  },
  {
    "episode": 75,
    "rewards": {
      "adversary_0": 0.0,
      "adversary_1": 0.0,
      "adversary_2": 0.0,
      "agent_0": -33.657418783839304
    },
    "captures": 0,
    "done_reason": "max_cycles"
  },
  {
    "episode": 76,
    "rewards": {
      "adversary_0": 0.0,
      "adversary_1": 0.0,
      "adversary_2": 0.0,
      "agent_0": -211.3042340634317
    },
    "captures": 0,
    "done_reason": "max_cycles"
  },
  {
    "episode": 77,
    "rewards": {
      "adversary_0": 30.0,
      "adversary_1": 30.0,
      "adversary_2": 30.0,
      "agent_0": -639.888338761827
    },
    "captures": 3,
    "done_reason": "capture"
  },
  {
    "episode": 78,
    "rewards": {
      "adversary_0": 0.0,
      "adversary_1": 0.0,
      "adversary_2": 0.0,
      "agent_0": -35.95059682475789
    },
    "captures": 0,
    "done_reason": "max_cycles"
  },
  {
    "episode": 79,
    "rewards": {
      "adversary_0": 0.0,
      "adversary_1": 0.0,
      "adversary_2": 0.0,
      "agent_0": -85.0497805123912
    },
    "captures": 0,
    "done_reason": "max_cycles"
  },
  {
    "episode": 80,
    "rewards": {
      "adversary_0": 0.0,
      "adversary_1": 0.0,
      "adversary_2": 0.0,
      "agent_0": -95.1569525599347
    },
    "captures": 0,
    "done_reason": "max_cycles"
  },
  {
    "episode": 81,
    "rewards": {
      "adversary_0": 20.0,
      "adversary_1": 20.0,
      "adversary_2": 20.0,
      "agent_0": -20.3889297544824
    },
    "captures": 2,
    "done_reason": "capture"
  },
  {
    "episode": 82,
    "rewards": {
      "adversary_0": 20.0,
      "adversary_1": 20.0,
      "adversary_2": 20.0,
      "agent_0": -33.30234782619327
    },
    "captures": 2,
    "done_reason": "capture"
  },
  {
    "episode": 83,
    "rewards": {
      "adversary_0": 0.0,
      "adversary_1": 0.0,
      "adversary_2": 0.0,
      "agent_0": -295.173151910636
    },
    "captures": 0,
    "done_reason": "max_cycles"
  },
  {
    "episode": 84,
    "rewards": {
      "adversary_0": 0.0,
      "adversary_1": 0.0,
      "adversary_2": 0.0,
      "agent_0": 0.0
    },
    "captures": 0,
    "done_reason": "max_cycles"
  },
  {
    "episode": 85,
    "rewards": {
      "adversary_0": 0.0,
      "adversary_1": 0.0,
      "adversary_2": 0.0,
      "agent_0": 0.0
    },
    "captures": 0,
    "done_reason": "max_cycles"
  },
  {
    "episode": 86,
    "rewards": {
      "adversary_0": 0.0,
      "adversary_1": 0.0,
      "adversary_2": 0.0,
      "agent_0": 0.0
    },
    "captures": 0,
    "done_reason": "max_cycles"
  },
  {
    "episode": 87,
    "rewards": {
      "adversary_0": 0.0,
      "adversary_1": 0.0,
      "adversary_2": 0.0,
      "agent_0": -42.43224357231161
    },
    "captures": 0,
    "done_reason": "max_cycles"
  },
  {
    "episode": 88,
    "rewards": {
      "adversary_0": 0.0,
      "adversary_1": 0.0,
      "adversary_2": 0.0,
      "agent_0": -13.536817688545772
    },
    "captures": 0,
    "done_reason": "max_cycles"
  },
  {
    "episode": 89,
    "rewards": {
      "adversary_0": 0.0,
      "adversary_1": 0.0,
      "adversary_2": 0.0,
      "agent_0": -403.75243765894027
    },
    "captures": 0,
    "done_reason": "max_cycles"
  },
  {
    "episode": 90,
    "rewards": {
      "adversary_0": 0.0,
      "adversary_1": 0.0,
      "adversary_2": 0.0,
      "agent_0": -418.6672481331458
    },
    "captures": 0,
    "done_reason": "max_cycles"
  },
  {
    "episode": 91,
    "rewards": {
      "adversary_0": 30.0,
      "adversary_1": 30.0,
      "adversary_2": 30.0,
      "agent_0": -147.96554158589714
    },
    "captures": 3,
    "done_reason": "capture"
  },
  {
    "episode": 92,
    "rewards": {
      "adversary_0": 30.0,
      "adversary_1": 30.0,
      "adversary_2": 30.0,
      "agent_0": -80.33930792911704
    },
    "captures": 3,
    "done_reason": "capture"
  },
  {
    "episode": 93,
    "rewards": {
      "adversary_0": 0.0,
      "adversary_1": 0.0,
      "adversary_2": 0.0,
      "agent_0": -11.537527793989904
    },
    "captures": 0,
    "done_reason": "max_cycles"
  },
  {
    "episode": 94,
    "rewards": {
      "adversary_0": 0.0,
      "adversary_1": 0.0,
      "adversary_2": 0.0,
      "agent_0": -532.1439429592954
    },
    "captures": 0,
    "done_reason": "max_cycles"
  },
  {
    "episode": 95,
    "rewards": {
      "adversary_0": 20.0,
      "adversary_1": 20.0,
      "adversary_2": 20.0,
      "agent_0": -120.33260366681463
    },
    "captures": 2,
    "done_reason": "capture"
  },
  {
    "episode": 96,
    "rewards": {
      "adversary_0": 0.0,
      "adversary_1": 0.0,
      "adversary_2": 0.0,
      "agent_0": -249.18106823520793
    },
    "captures": 0,
    "done_reason": "max_cycles"
  },
  {
    "episode": 97,
    "rewards": {
      "adversary_0": 0.0,
      "adversary_1": 0.0,
      "adversary_2": 0.0,
      "agent_0": -314.1165665057925
    },
    "captures": 0,
    "done_reason": "max_cycles"
  },
  {
    "episode": 98,
    "rewards": {
      "adversary_0": 0.0,
      "adversary_1": 0.0,
      "adversary_2": 0.0,
      "agent_0": -3.931720849726103
    },
    "captures": 0,
    "done_reason": "max_cycles"
  },
  {
    "episode": 99,
    "rewards": {
      "adversary_0": 0.0,
      "adversary_1": 0.0,
      "adversary_2": 0.0,
      "agent_0": -239.5248771932078
    },
    "captures": 0,
    "done_reason": "max_cycles"
  }
]